assessment/SCTAssessmentReportTemplate.html
assessment/__init__.py
assessment/assessment.py
assessment/awssctcomplexitymatrix.csv
assessment/sct_input.csv
extensionmigrationassistant-0.1.5.dist-info/LICENSE.txt
extensionmigrationassistant-0.1.5.dist-info/METADATA
extensionmigrationassistant-0.1.5.dist-info/WHEEL
extensionmigrationassistant-0.1.5.dist-info/entry_points.txt
extensionmigrationassistant-0.1.5.dist-info/top_level.txt
extensionmigrationassistant-0.1.5.dist-info/RECORD
