Metadata-Version: 2.1
Name: extensionmigrationassistant
Version: 0.1.5
Summary: Description of your package
Home-page: https://github.com/dcgadmin/extensionmigrationassistant.git
Author: DataCloudGaze
Author-email: contact@datacloudgaze.com
License: MIT License
Classifier: Programming Language :: Python :: 3
Classifier: Development Status :: 4 - Beta
Classifier: License :: OSI Approved :: MIT License
Classifier: Operating System :: OS Independent
Classifier: Environment :: Console
Requires-Python: >=3.0
License-File: LICENSE.txt
Requires-Dist: Jinja2
Requires-Dist: matplotlib
Requires-Dist: numpy
Requires-Dist: pandas
Requires-Dist: psycopg2-binary
Requires-Dist: SQLAlchemy
